CHANGELOG.rst
LICENSE.txt
MANIFEST.in
README.rst
TODO.txt
VERSION.txt
setup.cfg
setup.py
asset/__init__.py
asset/isstr.py
asset/plugin.py
asset/resource.py
asset/symbol.py
asset/test.py
asset/test_plugin.py
asset.egg-info/PKG-INFO
asset.egg-info/SOURCES.txt
asset.egg-info/dependency_links.txt
asset.egg-info/requires.txt
asset.egg-info/top_level.txt
asset.egg-info/zip-safe
asset/test/data.csv
asset/test/data/file1.nl
asset/test/data/file2.nl
asset/test/data/subdir/subfile1.nl