Metadata-Version: 1.1
Name: asset
Version: 0.6.9
Summary: A package resource and symbol loading helper library.
Home-page: http://github.com/metagriffin/asset
Author: metagriffin
Author-email: mg.pypi@uberdev.org
License: GPLv3+
Keywords: python package pkg_resources asset resolve lookup loader
Platform: any
Classifier: Development Status :: 5 - Production/Stable
Classifier: Intended Audience :: Developers
Classifier: Programming Language :: Python
Classifier: Operating System :: OS Independent
Classifier: Natural Language :: English
Classifier: License :: OSI Approved :: GNU General Public License v3 or later (GPLv3+)
